MANIFEST.in
README
README.rst
setup.py
demo/ftp_test.py
networkdevice/__init__.py
networkdevice/cisco.py
networkdevice/junos.py
networkdevice/linux.py
networkdevice.egg-info/PKG-INFO
networkdevice.egg-info/SOURCES.txt
networkdevice.egg-info/dependency_links.txt
networkdevice.egg-info/requires.txt
networkdevice.egg-info/top_level.txt