Metadata-Version: 1.0
Name: networkdevice
Version: 0.4
Summary: Python modules to execut command on remote network device based on pexpect.
Home-page: https://github.com/guoyoooping/networkdevice
Author: Yongping Guo
Author-email: guoyoooping@163.com
License: GPLv3
Platform: UNKNOWN
